.requires
.test-requires
LICENSE
MANIFEST.in
README.rst
setup.py
subway.py
test_subway.py
tox.ini
subway.egg-info/PKG-INFO
subway.egg-info/SOURCES.txt
subway.egg-info/dependency_links.txt
subway.egg-info/entry_points.txt
subway.egg-info/requires.txt
subway.egg-info/top_level.txt